setup.py
dm/__init__.py
dm.xmlsec.binding.egg-info/PKG-INFO
dm.xmlsec.binding.egg-info/SOURCES.txt
dm.xmlsec.binding.egg-info/dependency_links.txt
dm.xmlsec.binding.egg-info/namespace_packages.txt
dm.xmlsec.binding.egg-info/not-zip-safe
dm.xmlsec.binding.egg-info/requires.txt
dm.xmlsec.binding.egg-info/top_level.txt
dm/xmlsec/__init__.py
dm/xmlsec/binding/LICENSE.txt
dm/xmlsec/binding/README.txt
dm/xmlsec/binding/VERSION.txt
dm/xmlsec/binding/__init__.py
dm/xmlsec/binding/tests.py
dm/xmlsec/binding/tests.txt
dm/xmlsec/binding/tmpl.py
dm/xmlsec/binding/resources/deskey.bin
dm/xmlsec/binding/resources/encrypt-element-tmpl.xml
dm/xmlsec/binding/resources/encrypt1-res.xml
dm/xmlsec/binding/resources/encrypt1-tmpl.xml
dm/xmlsec/binding/resources/encrypt2-doc.xml
dm/xmlsec/binding/resources/encrypt2-res.xml
dm/xmlsec/binding/resources/encrypt3-doc.xml
dm/xmlsec/binding/resources/encrypt3-res.xml
dm/xmlsec/binding/resources/rootcert.pem
dm/xmlsec/binding/resources/rsacert.pem
dm/xmlsec/binding/resources/rsakey.pem
dm/xmlsec/binding/resources/rsapub.pem
dm/xmlsec/binding/resources/sign1-res.xml
dm/xmlsec/binding/resources/sign1-tmpl.xml
dm/xmlsec/binding/resources/sign2-doc.xml
dm/xmlsec/binding/resources/sign2-res.xml
dm/xmlsec/binding/resources/sign3-doc.xml
dm/xmlsec/binding/resources/sign3-res.xml
dm/xmlsec/binding/resources/verify4-bad-res.xml
dm/xmlsec/binding/resources/verify4-bad-tmpl.xml
dm/xmlsec/binding/resources/verify4-res.xml
dm/xmlsec/binding/resources/verify4-tmpl.xml
src/_xmlsec.c
src/_xmlsec.pyx
src/cxmlsec.h
src/cxmlsec.pxd
src/lxml-version.h
src/lxml.etree.h
src/lxml.etree_api.h