Metadata-Version: 1.1
Name: dm.xmlsec.binding
Version: 1.0
Summary: Cython/lxml based binding for the XML security library -- for lxml 2.x
Home-page: http://pypi.python.org/pypi/dm.xmlsec.binding
Author: Dieter Maurer
Author-email: dieter@handshake.de
License: BSD
Keywords: encryption xml security digital signature cython lxml
Platform: UNKNOWN
Classifier: Development Status :: 5 - Production/Stable
Classifier: Intended Audience :: Developers
Classifier: License :: OSI Approved :: BSD License
Classifier: Operating System :: OS Independent
Classifier: Programming Language :: Python :: 2.4
Classifier: Programming Language :: Python :: 2.6
Classifier: Programming Language :: Python :: 2.7
Classifier: Operating System :: POSIX :: Linux
Classifier: Topic :: Utilities
